Workbook

Sheet README
B2: AI productivity and pricing evidence pack
B3: Insight | C3: This workbook is the source-of-truth dataset for the dossier “What is the real, quantified value of AI today?” Each numbered sheet is a chart-ready insight with source URLs and confidence notes.
B5: Source note | C5: Built from Statista Premium search results, CB Insights, academic papers, public macro sources, and vendor pricing pages compiled May 13, 2026.
B8: Sheet | C8: Purpose
B9: S01 Macro TFP | C9: Macro productivity estimates cluster far below “10x”: current estimates range from +0.07 to +1.5 pp/yr depending on assumptions.
B10: S02 Adoption Gap | C10: AI exposure is broad, but daily/intensive use remains much narrower than theoretical exposure.
B11: S03 Labor Exposure | C11: AI exposure is high in advanced economies, but exposure is not the same as displacement.
B12: S04 Task Experiments | C12: Controlled studies show strong task-level gains, mostly 14–55%, with important negative/null cases.
B13: S05 Sector Value Bands | C13: Value varies by workflow: writing and support are strong; senior complex software work is mixed.
B14: S06 Heterogeneity | C14: The most reliable effect is compression: junior/novice workers often gain more than experts.
B15: S07 Pricing Ladder | C15: 20–30% value uplift supports model change and moderate premiums, not 10x pricing.
B16: S08 Pricing Cases | C16: Intercom, Salesforce, Microsoft, GitHub, and foundation models show hybrid pricing patterns.
B17: S09 Value Calculator | C17: Simple auditable formula translating addressable hours and uplift into monthly price capacity.
... B19: Source Register | C19: All source URLs used in the workbook.
B21: Update: Value Increase Index layer
B22: S11-S15 add a common denominator for AI value: net AI Value Increase Index (AVII), sector comparisons, revenue/cost value mix, pricing-model implications, and booster-claim challenge logic.

Sheet S01 Macro TFP
B2: Macro productivity estimates are material, not 10x
B3: Insight | C3: The rigorous macro range is positive but modest: conservative estimates are around +0.07 to +0.6 pp annual TFP, while the optimistic Goldman scenario reaches +1.5 pp annual labor productivity during deployment.
B8: Source | C8: Year | D8: Annual uplift (pp) | E8: Metric | F8: Geography | G8: Caveat
B9: Acemoglu | C9: 2024 | D9: 0.07 | E9: TFP pp/yr | F9: US | G9: Conservative task-based model
B10: Penn Wharton/CBO | C10: 2025 | D10: 0.15 | E10: TFP pp/yr | F10: US | G10: Conservative midpoint of +0.1–0.2 pp/yr
B11: OECD low | C11: 2024 | D11: 0.25 | E11: TFP pp/yr | F11: US | G11: Low end of OECD range
B12: OECD high | C12: 2024 | D12: 0.6 | E12: TFP pp/yr | F12: US | G12: High end of OECD range
B13: McKinsey low | C13: 2023 | D13: 0.1 | E13: Labor prod. pp/yr | F13: Global | G13: Low end for gen AI alone
B14: McKinsey high | C14: 2023 | D14: 0.6 | E14: Labor prod. pp/yr | F14: Global | G14: High end for gen AI alone
B15: Goldman Sachs | C15: 2023 | D15: 1.5 | E15: Labor prod. pp/yr | F15: Global/US | G15: Optimistic deployment-decade scenario
B18: Sources
B19: Source | C19: URL
B20: Acemoglu / NBER | C20: https://www.nber.org/papers/w32487
B21: OECD Miracle or Myth | C21: https://www.oecd.org/en/publications/miracle-or-myth-assessing-the-macroeconomic-productivity-gains-from-artificial-intelligence_b524a072-en.html
B22: Goldman Sachs | C22: https://www.goldmansachs.com/insights/articles/generative-ai-could-raise-global-gdp-by-7-percent
B23: McKinsey Global Institute | C23: https://www.mckinsey.com/capabilities/tech-and-ai/our-insights/the-economic-potential-of-generative-ai-the-next-productivity-frontier

Sheet S02 Adoption Gap
B2: The macro-micro gap: exposure is broad, daily use is still narrow
B3: Insight | C3: Headline exposure/adoption figures are much larger than daily usage or work-hour penetration. That gap explains why strong task-level studies have not yet translated into a visible 10x macro outcome.
B8: Metric | C8: Share (%) | D8: Type | E8: Source
B9: US population using gen AI | C9: 39.4 | D9: Adoption | E9: Bick/Blandin/Deming
B10: Employed workers using at work weekly | C10: 23 | D10: Work usage | E10: Bick/Blandin/Deming
B11: Employed workers using daily | C11: 9 | D11: Daily usage | E11: Bick/Blandin/Deming
B12: Work hours assisted by gen AI - low | C12: 1 | D12: Intensity | E12: Bick/Blandin/Deming
B13: Work hours assisted by gen AI - high | C13: 7 | D13: Intensity | E13: Bick/Blandin/Deming
B14: Formal firm adoption | C14: 5.4 | D14: Formal adoption | E14: St. Louis Fed/Bick
B15: Country-level business adoption low | C15: 5 | D15: Business adoption | E15: OECD
B16: Country-level business adoption high | C16: 15 | D16: Business adoption | E16: OECD
B19: Sources
B20: Source | C20: URL
B21: NBER Rapid Adoption | C21: https://www.nber.org/papers/w32966
B22: St. Louis Fed Open Vault | C22: https://www.stlouisfed.org/open-vault/2025/oct/generative-ai-productivity-future-work
B23: OECD Ecoscope | C23: https://oecdecoscope.blog/2024/11/26/miracle-or-myth-assessing-the-macroeconomic-productivity-gains-from-artificial-intelligence/

Sheet S03 Labor Exposure
B2: Employment exposure is high, but exposure is not displacement
B3: Insight | C3: IMF and Goldman estimates show high partial exposure, especially in advanced economies. The pricing implication is that AI can affect many jobs, but only a subset of tasks and workflows are currently monetizable.
B8: Metric | C8: Share (%) | D8: Source | E8: Type
B9: Global employment exposed | C9: 40 | D9: IMF | E9: Exposure
B10: Advanced economies exposed | C10: 60 | D10: IMF | E10: Exposure
B11: Emerging markets exposed | C11: 40 | D11: IMF | E11: Exposure
B12: Low-income countries exposed | C12: 26 | D12: IMF | E12: Exposure
B13: US occupations with some exposure | C13: 67 | D13: Goldman Sachs | E13: Exposure
B14: US task substitution share | C14: 25 | D14: Goldman Sachs | E14: Substitution
B15: Work hours currently assisted - high | C15: 7 | D15: Bick/Blandin/Deming | E15: Current use
B18: Sources
B19: Source | C19: URL
B20: IMF AI and Global Economy | C20: https://www.imf.org/en/blogs/articles/2024/01/14/ai-will-transform-the-global-economy-lets-make-sure-it-benefits-humanity
B21: Goldman Sachs GDP impact | C21: https://www.goldmansachs.com/insights/articles/generative-ai-could-raise-global-gdp-by-7-percent
B22: NBER Rapid Adoption | C22: https://www.nber.org/papers/w32966

Sheet S04 Task Experiments
B2: Task-level gains are real, but bounded by task scope
B3: Insight | C3: The strongest experiments show 14–55% productivity gains, but complex expert software work shows null or negative results. This makes a broad 20–30% value thesis more defensible than a 10x claim.
B8: Function | C8: Study | D8: Effect (%) | E8: Metric | F8: Confidence | G8: Caveat
B9: Customer support | C9: Brynjolfsson/Li/Raymond | D9: 13.8 | E9: Issues resolved/hour | F9: Very high | G9: Novice +34%; experts ~0%
B10: Consulting | C10: HBS/BCG Jagged Frontier | D10: 25.1 | E10: Speed | F10: Very high | G10: Quality +40%; outside-frontier correctness -19pp
B11: Writing | C11: Noy & Zhang Science | D11: 40 | E11: Time reduction | F11: Very high | G11: Quality +18%
B12: Software simple task | C12: GitHub Copilot lab | D12: 55.8 | E12: Faster completion | F12: High within scope | G12: Narrow HTTP server task
B13: Enterprise software | C13: MIT/Accenture Copilot RCT | D13: 22 | E13: PRs/builds | F13: High | G13: Junior/high-workload gains higher
B14: Cross-industry email | C14: Dillon et al. Copilot RCT | D14: 31 | E14: Email time reduction | F14: Very high | G14: Meetings unchanged
B15: Public sector | C15: UK GDS Copilot | D15: 5.4 | E15: Day saved | F15: Low-medium | G15: Self-reported
B16: Experienced OS dev | C16: METR | D16: -19 | E16: Completion time | F16: Moderate | G16: AI slowed work in complex familiar repos
B19: Sources
B20: Source | C20: URL
B21: NBER Generative AI at Work | C21: https://www.nber.org/papers/w31161
B22: HBS Jagged Frontier | C22: https://www.hbs.edu/faculty/Pages/item.aspx?num=64700
B23: Noy & Zhang | C23: https://cepr.org/voxeu/columns/productivity-effects-generative-artificial-intelligence
B24: GitHub Copilot experiment | C24: https://arxiv.org/abs/2302.06590
B25: METR developer study | C25: https://metr.org/blog/2025-07-10-early-2025-ai-experienced-os-dev-study/

Sheet S05 Sector Value Bands
B2: Defensible value bands vary sharply by workflow
B3: Insight | C3: The pricing-safe claim is not “AI improves everything by 10x.” It is “AI improves specific workflows by measurable bands, with confidence varying by evidence quality.”
B8: Workflow | C8: Low effect (%) | D8: Central effect (%) | E8: High effect (%) | F8: Confidence | G8: Notes
B9: Routine writing / document drafting | C9: 20 | D9: 40 | E9: 65 | F9: High | G9: Document-centric work
B10: Professional knowledge work inside frontier | C10: 15 | D10: 25 | E10: 40 | F10: High | G10: Consulting-style tasks
B11: Customer support novice agents | C11: 15 | D11: 35 | E11: 46 | F11: Very high | G11: High-volume support
B12: Customer support expert agents | C12: 0 | D12: 0 | E12: 5 | F12: High | G12: Expert ceiling
B13: Software dev standard tasks | C13: 10 | D13: 22 | E13: 56 | F13: Moderate-high | G13: Junior/mid, greenfield
B14: Software dev senior complex repos | C14: -19 | D14: 0 | E14: 10 | F14: Moderate | G14: Risk of slowdown
B15: E-commerce conversion workflows | C15: 0 | D15: 8 | E15: 16 | F15: High | G15: Workflow-specific revenue uplift
B16: Email / admin work | C16: 10 | D16: 31 | E16: 40 | F16: High | G16: Heavy users
B17: Legal routine contract review | C17: 50 | D17: 200 | E17: 300 | F17: Low-medium | G17: Narrow NDA-type tasks
B20: Sources
B21: Source | C21: URL
B22: Task evidence synthesis | C22: Multiple primary sources listed in Source Register

Sheet S06 Heterogeneity
B2: The most reliable AI effect is skill compression
B3: Insight | C3: Across support, consulting, and writing, the largest gains often go to novice or below-median users. This is powerful for onboarding and high-volume support, but weakens flat per-seat pricing for senior expert teams.
B8: Function | C8: Higher-gain segment | D8: Higher-gain effect (%) | E8: Lower-gain segment | F8: Lower-gain effect (%) | G8: Source
B9: Customer support | C9: Low-skill / novice | D9: 34 | E9: Experienced / high-skill | F9: 0 | G9: Brynjolfsson et al.
B10: Customer support tenure | C10: New workers | D10: 46 | E10: Expert tenure | F10: 0 | G10: Brynjolfsson et al.
B11: Consulting | C11: Below-median performers | D11: 43 | E11: Above-median performers | F11: 17 | G11: HBS/BCG
B12: Writing | C12: Below-median writers | D12: Larger quality gains | E12: High performers | F12: Smaller gains | G12: Noy & Zhang
B13: Content creation | C13: Adjacent outsiders | D13: Near experts | E13: Distant outsiders | F13: 13% below experts | G13: HBS Wall Effect
B16: Sources
B17: Source | C17: URL
B18: NBER Generative AI at Work | C18: https://www.nber.org/papers/w31161
B19: HBS Jagged Frontier | C19: https://www.hbs.edu/faculty/Pages/item.aspx?num=64700
B20: Noy & Zhang | C20: https://cepr.org/voxeu/columns/productivity-effects-generative-artificial-intelligence
B21: HBS GenAI Wall Effect | C21: https://www.library.hbs.edu/working-knowledge/gen-ai-boosts-productivity-but-cant-turn-novices-into-experts

Sheet S07 Pricing Ladder
B2: Value uplift determines pricing model, not just price level
B3: Insight | C3: A 20–30% productivity gain is enough to justify AI meters, credits, and moderate premium tiers. It is not enough to justify 10x price increases unless the product replaces a measurable labor cost or revenue bottleneck.
B8: Value uplift zone | C8: Buyer response | D8: Pricing model implication | E8: Vendor strategy
B9: <10% | C9: Skepticism; bundle into base | D9: No premium; retention feature | E9: Bundle/free AI
B10: 10–20% | C10: Cautious adoption with proof | D10: Hybrid seat + usage; modest premium | E10: $5–15/user/month AI add-on
B11: 20–30% | C11: Separate AI line item possible | D11: Consumption/outcome meter plus seat | E11: 20–50% premium on base tier
B12: 30–60% | C12: Labor-budget shift possible | D12: Outcome/resolution pricing viable | E12: Shared savings or agent-as-FTE
B13: >60% | C13: Full substitution possible in narrow workflows | D13: Outcome pricing at fraction of value | E13: 10–20% of value created, not 10x list price
B16: Sources
B17: Source | C17: URL
B18: BCG AI software pricing | C18: https://www.bcg.com/publications/2025/rethinking-b2b-software-pricing-in-the-era-of-ai
B19: Bain seat pricing and AI | C19: https://www.bain.com/insights/per-seat-software-pricing-isnt-dead-but-new-models-are-gaining-steam/
B20: a16z outcome pricing | C20: https://a16z.com/newsletter/december-2024-enterprise-newsletter-ai-is-driving-a-shift-towards-outcome-based-pricing/

Sheet S08 Pricing Cases
B2: AI vendors are moving to hybrid pricing, not pure 10x premiums
B3: Insight | C3: The market evidence shows hybrid pricing: seats remain for predictability, while credits, actions, outcomes, and tokens meter AI-specific value and cost.
B8: Company | C8: Model | D8: Price point | E8: Value metric | F8: Value evidence | G8: Key caveat
B9: Intercom Fin | C9: Outcome/resolution | D9: $0.99 per outcome | E9: Resolved issue or completed workflow | F9: Human query cost often $5–10; 80–90% per-resolution savings | G9: Cost rises as AI succeeds; outcome definition disputed
B10: Salesforce Agentforce | C10: Flex credits + seats | D10: $500 per 100k credits; $2/conversation still listed; $125/user/month flat access | E10: Agent action, conversation, or employee agent access | F10: Granular action meter after $2/conversation backlash | G10: Billing complexity and observability burden
B11: Microsoft 365 Copilot | C11: Seat | D11: $30/user/month enterprise | E11: Productivity uplift | F11: Forrester TEI 132–353% projected ROI | G11: Paid adoption selective; commissioned ROI
B12: GitHub Copilot | C12: Seat to AI credits | D12: $19 Business; $39 Enterprise | E12: Developer productivity / AI credits | F12: Lab tasks +55.8%; enterprise RCT +22% PRs | G12: Complex repo studies show null/negative risks
B13: OpenAI / Anthropic | C13: Token usage | D13: Per 1M input/output tokens | E13: Tokens processed | F13: Cost floor for application-layer AI | G13: Runaway usage and margin compression risk
B16: Sources
B17: Source | C17: URL
B18: Intercom pricing | C18: https://www.intercom.com/pricing
B19: Salesforce Agentforce pricing | C19: https://www.salesforce.com/agentforce/pricing/
B20: Microsoft Copilot ROI | C20: https://www.microsoft.com/en-us/microsoft-365/blog/2024/10/17/microsoft-365-copilot-drove-up-to-353-roi-for-small-and-medium-businesses-new-study/
B21: GitHub Copilot docs | C21: https://docs.github.com/en/copilot/get-started/plans
B22: OpenAI API pricing | C22: https://developers.openai.com/api/docs/pricing

Sheet S09 Value Calculator
B2: Simple value-to-price calculator
B3: Insight | C3: This sheet translates workflow-level productivity into monthly value and a defensible price ceiling. Formulas are live so users can change assumptions.
B8: Role / workflow | C8: Loaded hourly cost ($) | D8: Addressable hours / week | E8: Productivity uplift (%) | F8: Recoverable share (%) | G8: Gross value / week ($) | H8: Monthly value ($) | I8: Target ROI multiple | J8: Defensible monthly price ($) | K8: Notes
B9: Knowledge worker - document work | C9: 80 | D9: 10 | E9: 0.25 | F9: 0.5 | G9: =C9*D9*E9 -> 200 | H9: =F9*4.33 -> 2.165 | I9: 10 | J9: =G9/H9 -> 92.378753 | K9: Central 20–30% uplift; only addressable tasks count
B10: Customer support novice agent | C10: 35 | D10: 30 | E10: 0.35 | F10: 0.7 | G10: =C10*D10*E10 -> 367.5 | H10: =F10*4.33 -> 3.031 | I10: 10 | J10: =G10/H10 -> 121.24711 | K10: High-volume support; stronger evidence
B11: Senior software engineer - complex repo | C11: 120 | D11: 20 | E11: 0 | F11: 0.3 | G11: =C11*D11*E11 -> 0 | H11: =F11*4.33 -> 1.299 | I11: 10 | J11: =G11/H11 -> 0 | K11: METR risk: zero/negative central case
B12: Junior software developer - standard tasks | C12: 70 | D12: 20 | E12: 0.22 | F12: 0.5 | G12: =C12*D12*E12 -> 308 | H12: =F12*4.33 -> 2.165 | I12: 10 | J12: =G12/H12 -> 142.26328 | K12: Enterprise PR/build evidence
B13: Legal routine contract review | C13: 150 | D13: 8 | E13: 0.5 | F13: 0.5 | G13: =C13*D13*E13 -> 600 | H13: =F13*4.33 -> 2.165 | I13: 10 | J13: =G13/H13 -> 277.13626 | K13: Narrow routine review only
B14: Sales/marketing content | C14: 75 | D14: 12 | E14: 0.3 | F14: 0.5 | G14: =C14*D14*E14 -> 270 | H14: =F14*4.33 -> 2.165 | I14: 10 | J14: =G14/H14 -> 124.71132 | K14: Writing/content evidence
B17: Sources
B18: Source | C18: URL
B19: Task-level evidence sources | C19: See S04 and S05
B20: Pricing ladder framework | C20: See S07 and S08

Sheet S10 Statista Benchmarks
B2: Statista benchmark layer
B3: Insight | C3: Statista provides market/adoption context rather than causal productivity proof: it shows workplace adoption, function-level gen AI use, workforce-impact expectations, and long-term AI labor-productivity forecasts.
B8: Statista item | C8: Value | D8: Unit | E8: Geography | F8: Original source | G8: Statista URL | H8: Interpretation
B9: AI adoption vs generative AI adoption, marketing & sales | C9: 14 | D9: Percent using gen AI | E9: Worldwide | F9: McKinsey / Stanford Medicine via Statista | G9: https://cashmere.io/v/klMFtxkBx | H9: Marketing and sales had nearly 14% generative AI adoption in 2023.
B10: Impact of AI on workforce worldwide | C10: 42 | D10: Percent transformational impact | E10: Worldwide | F10: Thomson Reuters via Statista | G10: https://cashmere.io/v/B7qHhEH06 | H10: 42% expected AI/GenAI to have transformational impact on profession over five years.
B11: Impact of AI on workforce worldwide | C11: 36 | D11: Percent high impact | E11: Worldwide | F11: Thomson Reuters via Statista | G11: https://cashmere.io/v/B7qHhEH06 | H11: 36% expected high impact.
B12: Artificial intelligence impact on labor productivity in 2035 | C12: 37 | D12: Percent increase vs baseline | E12: Sweden | F12: Accenture / Frontier Economics via Statista | G12: https://cashmere.io/v/kGsLIAodH | H12: Highest selected-country labor-productivity uplift estimate in source.
B13: Generative AI adoption in India marketing | C13: 73 | D13: Percent expectation | E13: India | F13: Mobile Marketing Association via Statista | G13: https://cashmere.io/v/GGNrDNXhF | H13: Marketers believed AI would enhance marketing without replacing human creativity/expertise.
B14: UAE generative AI adoption | C14: 52 | D14: Percent actively deploying | E14: UAE | F14: IBM via Statista | G14: https://cashmere.io/v/Z6u4doJKR | H14: Employees reported company actively deploying gen AI.
B15: Enterprise productivity software market size | C15: 501.3 | D15: USD billions | E15: Worldwide | F15: GP Bullhound via Statista | G15: https://cashmere.io/v/xdtU59GOw | H15: Forecast global enterprise productivity software revenue by 2025.

Sheet Source Register
B2: Source register
B3: Insight | C3: Canonical URLs used across the evidence pack. Use this sheet when rebuilding the report or creating a deck from the workbook.
B8: Source | C8: Use | D8: URL
B9: Acemoglu, Simple Macroeconomics of AI | C9: Macro productivity | D9: https://www.nber.org/papers/w32487
B10: Bick, Blandin & Deming, Rapid Adoption | C10: Adoption/time savings | D10: https://www.nber.org/papers/w32966
B11: St. Louis Fed, Generative AI Productivity | C11: Adoption/time savings | D11: https://www.stlouisfed.org/open-vault/2025/oct/generative-ai-productivity-future-work
B12: IMF, AI Will Transform Global Economy | C12: Labor exposure | D12: https://www.imf.org/en/blogs/articles/2024/01/14/ai-will-transform-the-global-economy-lets-make-sure-it-benefits-humanity
B13: OECD, Miracle or Myth | C13: Macro productivity | D13: https://www.oecd.org/en/publications/miracle-or-myth-assessing-the-macroeconomic-productivity-gains-from-artificial-intelligence_b524a072-en.html
B14: PwC AI Jobs Barometer | C14: Revenue/wages/jobs | D14: https://www.pwc.com/gx/en/services/ai/ai-jobs-barometer.html
B15: McKinsey Economic Potential of GenAI | C15: Economic potential | D15: https://www.mckinsey.com/capabilities/tech-and-ai/our-insights/the-economic-potential-of-generative-ai-the-next-productivity-frontier
B16: Goldman Sachs GDP estimate | C16: Macro optimism | D16: https://www.goldmansachs.com/insights/articles/generative-ai-could-raise-global-gdp-by-7-percent
B17: NBER Generative AI at Work | C17: Customer support RCT | D17: https://www.nber.org/papers/w31161
B18: HBS/BCG Jagged Frontier | C18: Consulting RCT | D18: https://www.hbs.edu/faculty/Pages/item.aspx?num=64700
B19: GitHub Copilot experiment | C19: Software dev lab RCT | D19: https://arxiv.org/abs/2302.06590
... B36: Statista: Global enterprise productivity software market size 2025 | C36: Market context | D36: https://cashmere.io/v/xdtU59GOw
B37: Anthropic labor-market impacts | C37: https://www.anthropic.com/research/labor-market-impacts | D37: Theoretical vs observed exposure, automation/augmentation weighting, employment tests | E37: Primary AI lab research | F37: S15
B38: Anthropic Economic Index March 2026 | C38: https://www.anthropic.com/research/economic-index-march-2026-report | D38: Task coverage, augmentation/automation, usage concentration, task wage/value | E38: Primary AI lab research | F38: S15
B39: Axios / Dario Amodei interview | C39: https://www.axios.com/2025/05/28/ai-jobs-white-collar-unemployment-anthropic | D39: Entry-level job loss and unemployment claims | E39: Media interview | F39: S15
B40: CNBC / Jensen Huang | C40: https://www.cnbc.com/2025/05/28/nvidia-ceo-jensen-huang-youll-lose-your-job-to-somebody-who-uses-ai.html | D40: AI user replacing non-user narrative | E40: Media interview | F40: S15
B41: Fortune / Sam Altman AI washing | C41: https://fortune.com/article/sam-altman-ai-washing-tech-layoffs/ | D41: AI washing and displacement comments | E41: Media interview/reporting | F41: S15
B42: Mass General Brigham AI scribes | C42: https://www.massgeneralbrigham.org/en/about/newsroom/press-releases/ai-scribes-linked-to-modest-reductions-in-ehr-documentation-time | D42: Healthcare documentation time and revenue impact | E42: Healthcare study summary | F42: S12
B43: Thomson Reuters Future of Professionals | C43: https://www.thomsonreuters.com/en/press-releases/2024/july/ai-set-to-save-professionals-12-hours-per-week-by-2029 | D43: Legal/tax/risk time-saving survey | E43: Vendor survey | F43: S12
B44: McKinsey product design | C44: https://www.mckinsey.com/capabilities/tech-and-ai/our-insights/generative-ai-fuels-creative-physical-product-design-but-is-no-magic-wand | D44: Product design cycle-time and caveats | E44: Consulting analysis | F44: S12
B45: HBS value stick | C45: https://online.hbs.edu/blog/post/value-based-strategy | D45: WTP, price, cost, value sharing | E45: Academic/business framework | F45: S11

Sheet S11 Value Index Method
B2: AI Value Increase Index (AVII): common denominator
B3: AVII converts time savings, throughput, quality, risk, revenue lift, and review drag into one net economic value-uplift percentage. Baseline 100 = current workflow value pool; AVII 124 = 24% net value uplift.
B5: Component | C5: Formula / treatment | D5: Interpretation | E5: Examples
B6: Baseline value pool | C6: Addressable revenue contribution margin + addressable labor cost + quantified risk/quality value | D6: The denominator. Prevents 55% task speed from becoming a fake 55% company productivity claim. | E6: Support cost pool; legal billable/rework pool; clinician documentation burden; developer throughput value
B7: Revenue value | C7: Incremental revenue × gross margin × attribution confidence | D7: Use only where AI can plausibly increase demand, conversion, win rate, price, or capacity sold. | E7: Sales conversion, e-commerce uplift, additional patient visits, more billable work
B8: Cost value | C8: Addressable cost × productivity uplift × recoverable share | D8: Most AI value lands here today; discount heavily when saved time is not converted into fewer hours, lower cost, or more output. | E8: Hours saved, lower cost per ticket, faster document drafting
B9: Quality/risk value | C9: Avoided error, compliance risk, burnout, churn, or quality loss translated into money | D9: Real but harder to prove. Include separately to avoid mixing soft benefits into direct cost savings. | E9: Lower escalation, less burnout, better first draft quality
B10: AI/review drag | C10: Tool cost + implementation cost + human verification/rework + governance overhead | D10: The deduction that stops theoretical automation from becoming real value too quickly. | E10: Legal review, code review, clinical sign-off, hallucination checks
B11: Net AVII uplift | C11: Revenue value + cost value + quality/risk value - AI/review drag | D11: The comparable index used across industries and pricing models. | E11: 24% net value uplift means value pool moves from 100 to 124
B12: Revenue-weighted AVII | C12: Net AVII × (1.0 × revenue share + 0.6 × cost share + 0.8 × risk/quality share) | D12: A pricing-salience version: buyers usually respond more strongly to growth stories than pure cost savings. | E12: A 20% mostly-cost case may price weaker than a 12% revenue case
B16: Important: AVII is a valuation/indexing layer, not a new empirical study. It normalizes reported evidence into a pricing-relevant common denominator and makes assumptions explicit.

Sheet S12 Sector Value Index
B2: Sector-level AI Value Increase Index
B3: Central estimates normalize the evidence into net economic value uplift. The split across revenue, cost, and quality/risk is directional and should be adjusted for a specific product or customer workflow.
B5: Sector / workflow | C5: Primary value metric | D5: Revenue uplift | E5: Cost decrease | F5: Quality / risk value | G5: AI / review drag | H5: Net AVII uplift | I5: Index (100+uplift) | J5: Revenue-weighted AVII | K5: Replaceability score | L5: Pricing implication | M5: Evidence anchor | N5: Confidence
B6: Customer support | C6: Resolved issues per hour / cost per resolution | D6: 0.02 | E6: 0.23 | F6: 0.01 | G6: 0.05 | H6: =D6+E6+F6-G6 -> 0.21 | I6: =100+H6*100 -> 121 | J6: =H6*(0.15*1+0.8*0.6+0.05*0.8) -> 0.1407 | K6: 4.5 | L6: Outcome or resolution pricing where attribution is clean; fallback to seat + resolution credits | M6: NBER support + Intercom/Salesforce pricing | N6: High
B7: Routine writing / content | C7: Time to accepted draft + quality | D7: 0.05 | E7: 0.22 | F7: 0.02 | G7: 0.05 | H7: =D7+E7+F7-G7 -> 0.24 | I7: =100+H7*100 -> 124 | J7: =H7*(0.2*1+0.7*0.6+0.1*0.8) -> 0.168 | K7: 3 | L7: Seat + usage credits; outcome pricing only for measurable content ops | M7: Noy-Zhang + HBS/BCG | N7: High
B8: Legal / compliance | C8: Hours saved in research, drafting, review | D8: 0.04 | E8: 0.14 | F8: 0.01 | G8: 0.04 | H8: =D8+E8+F8-G8 -> 0.15 | I8: =100+H8*100 -> 115 | J8: =H8*(0.25*1+0.65*0.6+0.1*0.8) -> 0.108 | K8: 3.5 | L8: Matter/task pricing for document-heavy workflows; seat pricing where lawyer judgment remains central | M8: Thomson Reuters + Anthropic exposure | N8: Moderate
B9: Software engineering | C9: PRs, builds, cycle time | D9: 0.04 | E9: 0.12 | F9: 0 | G9: 0.05 | H9: =D9+E9+F9-G9 -> 0.11 | I9: =100+H9*100 -> 111 | J9: =H9*(0.25*1+0.7*0.6+0.05*0.8) -> 0.0781 | K9: 3 | L9: Seat + metered credits; avoid 10x claims for senior complex repos | M9: GitHub/MIT/METR | N9: Moderate-high
B10: Sales / outbound | C10: Qualified pipeline and conversion | D10: 0.08 | E10: 0.05 | F10: 0 | G10: 0.04 | H10: =D10+E10+F10-G10 -> 0.09 | I10: =100+H10*100 -> 109 | J10: =H10*(0.6*1+0.35*0.6+0.05*0.8) -> 0.0765 | K10: 3.5 | L10: Usage or outcome-proxy pricing per enriched lead, meeting, or qualified account; avoid full revenue share unless attribution is proven | M10: Anthropic API automation patterns | N10: Low-moderate
B11: Healthcare documentation | C11: Documentation time, EHR time, burnout | D11: 0.01 | E11: 0.07 | F11: 0.05 | G11: 0.03 | H11: =D11+E11+F11-G11 -> 0.1 | I11: =100+H11*100 -> 110 | J11: =H11*(0.1*1+0.6*0.6+0.3*0.8) -> 0.07 | K11: 2.5 | L11: Per-clinician seat or per-encounter usage; outcome pricing hard unless tied to visits or documentation KPIs | M11: JAMA/Mass General Brigham + AMA | N11: Moderate
B12: Product design / architecture | C12: Design-cycle compression + concept volume | D12: 0.05 | E12: 0.1 | F12: 0.03 | G12: 0.06 | H12: =D12+E12+F12-G12 -> 0.12 | I12: =100+H12*100 -> 112 | J12: =H12*(0.3*1+0.55*0.6+0.15*0.8) -> 0.09 | K12: 2.5 | L12: Premium seat + project credits; outcome pricing weak unless tied to cycle-time milestones | M12: McKinsey product design | N12: Low-moderate
B13: General knowledge work | C13: Email, docs, coordination | D13: 0.02 | E13: 0.1 | F13: 0.01 | G13: 0.03 | H13: =D13+E13+F13-G13 -> 0.1 | I13: =100+H13*100 -> 110 | J13: =H13*(0.2*1+0.7*0.6+0.1*0.8) -> 0.07 | K13: 2 | L13: Seat-based AI add-on or bundled AI; outcome pricing usually too hard | M13: Dillon et al. Copilot + St. Louis Fed | N13: Moderate

Sheet S13 Rev Cost Mix
B2: Revenue versus cost mix of AI value
B3: This sheet separates economic value created from pricing salience. If most value is cost saving, the price ceiling is usually lower than a revenue-growth story with the same net economic uplift.
B5: Sector / workflow | C5: Revenue share of value | D5: Cost share of value | E5: Quality/risk share | F5: Net AVII uplift | G5: Revenue-weighted AVII | H5: Buyer salience note
B6: Customer support | C6: 0.15 | D6: 0.8 | E6: 0.05 | F6: ='S12 Sector Value Index'!H6 -> 0.21 | G6: ='S12 Sector Value Index'!J6 -> 0.1407 | H6: Mostly cost; outcome pricing works only because resolution is measurable
B7: Routine writing / content | C7: 0.2 | D7: 0.7 | E7: 0.1 | F7: ='S12 Sector Value Index'!H7 -> 0.24 | G7: ='S12 Sector Value Index'!J7 -> 0.168 | H7: Cost/time story; revenue story needs distribution/conversion proof
B8: Legal / compliance | C8: 0.25 | D8: 0.65 | E8: 0.1 | F8: ='S12 Sector Value Index'!H8 -> 0.15 | G8: ='S12 Sector Value Index'!J8 -> 0.108 | H8: Billable-hour economics complicate buyer and seller incentives
B9: Software engineering | C9: 0.25 | D9: 0.7 | E9: 0.05 | F9: ='S12 Sector Value Index'!H9 -> 0.11 | G9: ='S12 Sector Value Index'!J9 -> 0.0781 | H9: Faster shipping can be revenue-framed, but attribution is weak
B10: Sales / outbound | C10: 0.6 | D10: 0.35 | E10: 0.05 | F10: ='S12 Sector Value Index'!H10 -> 0.09 | G10: ='S12 Sector Value Index'!J10 -> 0.0765 | H10: Best revenue narrative, but evidence and attribution are weaker
B11: Healthcare documentation | C11: 0.1 | D11: 0.6 | E11: 0.3 | F11: ='S12 Sector Value Index'!H11 -> 0.1 | G11: ='S12 Sector Value Index'!J11 -> 0.07 | H11: Burnout and quality matter but are harder to price than visits
B12: Product design / architecture | C12: 0.3 | D12: 0.55 | E12: 0.15 | F12: ='S12 Sector Value Index'!H12 -> 0.12 | G12: ='S12 Sector Value Index'!J12 -> 0.09 | H12: Cycle-time value is credible if product launch economics are known
B13: General knowledge work | C13: 0.2 | D13: 0.7 | E13: 0.1 | F13: ='S12 Sector Value Index'!H13 -> 0.1 | G13: ='S12 Sector Value Index'!J13 -> 0.07 | H13: Diffuse value; best priced as seat or bundle

Sheet S14 Pricing Model Matrix
B2: AI pricing model implication by replaceability and measurability
B3: The more AI replaces a measurable human task, the more pricing can move toward outcomes. Where AI only augments human judgment or coordination, seat/usage models remain more defensible.
B5: Replaceability | C5: Outcome measurability | D5: Human verification burden | E5: Recommended pricing model | F5: Why | G5: Example workflows
B6: High | C6: High | D6: Low-medium | E6: Outcome pricing | F6: Vendor can credibly price per resolved/accepted business result because value is observable and attribution is clean. | G6: Support resolution, document classification, data extraction
B7: High | C7: Medium | D7: Medium | E7: Output-unit pricing | F7: AI performs a task, but the buyer still needs acceptance criteria and audit rights. | G7: Drafted contracts, enriched leads, generated reports
B8: Medium | C8: Medium | D8: Medium | E8: Seat + usage credits | F8: Human remains the unit of work, but usage varies enough to justify metering. | G8: Developer copilots, analyst copilots, legal assistants
B9: Medium | C9: Low | D9: High | E9: Seat add-on or bundled AI | F9: Value is real but diffuse across many tasks; buyers resist outcome pricing because attribution is weak. | G9: General productivity suites, enterprise search
B10: Low | C10: Low | D10: High | E10: Bundle / retention feature | F10: AI is a feature enhancer rather than a separate economic product; pricing power is limited. | G10: Meeting summaries, basic drafting, internal Q&A

Sheet S15 Booster Claims
B2: Booster claims versus normalized value evidence
B3: This sheet challenges large AI-displacement claims by translating them into the same denominator: observed net value uplift and pricing implications, not theoretical capability alone.
B5: Claim / narrative | C5: Source | D5: Implied magnitude | E5: What the evidence actually measures | F5: Common-denominator challenge | G5: Pricing implication
B6: AI could eradicate half of entry-level white-collar jobs and push unemployment to 10-20% | C6: Dario Amodei via Axios | D6: Role-level displacement | E6: Anthropic also shows a large gap between theoretical and observed exposure; unemployment impact so far is small/insignificant in its labor-market tests | F6: Treat as exposure risk, not realized value. AVII requires observed usage, recoverability, and review drag. | G6: Outcome pricing plausible only in narrow automated tasks; broad 10x pricing is unsupported
B7: You will be replaced by someone who uses AI | C7: Jensen Huang via CNBC | D7: Worker-level productivity competition | E7: This is closer to augmentation than full replacement; it implies skill-biased productivity gains | F7: Supports 20-40% workflow uplift framing rather than 80% workforce reduction | G7: Seat + usage pricing remains logical because the human remains the unit
B8: Some layoffs are AI washing, but real displacement will become palpable | C8: Sam Altman via Fortune | D8: Mixed displacement and adoption narrative | E8: Article cites counter-evidence showing no major macro labor shift yet and executive surveys with little employment impact so far | F8: Use adoption and labor evidence as lagging indicators, not vendor claims | G8: Pricing should be tied to measurable workflow value, not hype narrative
B9: Claude has done at least a quarter of tasks in 49% of jobs | C9: Anthropic Economic Index | D9: Task coverage across jobs | E9: The metric is usage/task coverage, not job replacement or net economic value | F9: Convert coverage into AVII using addressable share × uplift × recoverability - drag | G9: Good for identifying where usage meters may emerge
B10: Computer/math tasks are theoretically 94% exposed | C10: Anthropic labor-market impacts | D10: Theoretical task feasibility | E10: Observed exposure for computer/math is much lower at 33%; model limits, legal constraints, software requirements, and human verification slow diffusion | F10: Theoretical exposure is not the denominator for price. Observed net value is. | G10: Use hybrid pricing; avoid assuming full automation
